{
  "cookies": [
    {
      "name": "_ga",
      "value": "GA1.2.907674628.1692718781",
      "domain": ".mixtelematics.com",
      "path": "/",
      "expires": 1727278781.274724,
      "httpOnly": false,
      "secure": false,
      "sameSite": "Lax"
    },
    {
      "name": "_gid",
      "value": "GA1.2.2118321156.1692718781",
      "domain": ".mixtelematics.com",
      "path": "/",
      "expires": 1692805181,
      "httpOnly": false,
      "secure": false,
      "sameSite": "Lax"
    },
    {
      "name": "_gat",
      "value": "1",
      "domain": ".mixtelematics.com",
      "path": "/",
      "expires": 1692718841,
      "httpOnly": false,
      "secure": false,
      "sameSite": "Lax"
    },
    {
      "name": "selectionCriteria.BaseApp.GlobalSelectionCriteria",
      "value": "%7B%22lastUserLanguageCookie%22%3A%22en_gb%22%7D",
      "domain": "integration.mixtelematics.com",
      "path": "/",
      "expires": 1724254783,
      "httpOnly": false,
      "secure": false,
      "sameSite": "Lax"
    },
    {
      "name": "token",
      "value": "33c44b66-3de5-4fab-8a3c-fa66a4ded44e",
      "domain": "integration.mixtelematics.com",
      "path": "/",
      "expires": 1692722386.842463,
      "httpOnly": true,
      "secure": true,
      "sameSite": "Strict"
    },
    {
      "name": "AWSALBCORS",
      "value": "LyBe7ZnBOuaSkcYKtNRR7tyrUFitkiSdMx4Kuefqw04tv8AOxVau7JFng2f1fHnIfYAm83fl7ArgZ7guZgdKmpqf4o+r1VILDG6XwMv/vzhdxAFJP1M1TtN+piCy",
      "domain": "operationsapi.mixdevelopment.com",
      "path": "/",
      "expires": 1693323584.597913,
      "httpOnly": false,
      "secure": true,
      "sameSite": "None"
    },
    {
      "name": "_ga_GQ2YD2JCKS",
      "value": "GS1.2.1692718783.1.1.1692718784.0.0.0",
      "domain": ".mixtelematics.com",
      "path": "/",
      "expires": 1727278784.990479,
      "httpOnly": false,
      "secure": false,
      "sameSite": "Lax"
    }
  ],
  "origins": [
    {
      "origin": "https://integration.mixtelematics.com",
      "localStorage": [
        {
          "name": "ZD-suid",
          "value": "{\"id\":\"8f91f1500f2f49bea725cd658d9b98a9\",\"expiry\":1692719686394,\"tabs\":{\"count\":1,\"expiry\":0}}"
        },
        {
          "name": "Timeline.TimelineSelectionCriteria.viewDate",
          "value": "null"
        },
        {
          "name": "ZD-buid",
          "value": "c6fddf35d2ad4111ac1e22ab49844a4b"
        },
        {
          "name": "ZD-store",
          "value": "{\"activeEmbed\":\"helpCenterForm\",\"widgetShown\":false,\"is_chatting\":false}"
        },
        {
          "name": "ZD-zE_oauth",
          "value": "{\"id\":\"3aee40cc3f21d1ed342c04e22844f3afd3cb27ae\",\"token\":\"0f1df5fa1908b39102079e2714251b283696269bb2dd8b04cecac16447d3ea12\",\"expiry\":1692725987,\"createdAt\":1692718787,\"webToken\":\"eyJhbGciOiJIUzI1NiIsInR5cCI6IkpXVCJ9.eyJuYW1lIjoiQnJhbmRvbiBPbGNrZXJzIiwiZW1haWwiOiJicmFuZG9uLm9sY2tlcnNAbWl4dGVsZW1hdGljcy5jb20iLCJpYXQiOiIxNjkyNzE4Nzg2IiwianRpIjoiMTQzMDcyNzc0NjIzMjAyOTE4NCIsImV4cCI6MTY5MjcyNTk4Nn0.fbKY7Xy0bOfhoxngoYL4NGClrRDfTmLaE5-SL5KTyVg\"}"
        }
      ]
    }
  ]
}